studlis/__init__.py
studlis/__main__.py
studlis/authprovider.py
studlis/configure.py
studlis/database.py
studlis/docvs.py
studlis/icon.py
studlis/logger.py
studlis/scan.py
studlis/studlis.py
studlis/studlis_direct.py
studlis/user.py
studlis/util.py
studlis/webserver.py
studlis/projects/__init__.py
studlis/projects/project.py
studlis/static/__init__.py
studlis/static/canvas.js
studlis/static/editor.js
studlis/static/engine.js
studlis/static/lang.js
studlis/static/main.css
studlis/static/ui.css
studlis/static/ui.js
studlis/static/bootstrap5.3/__init__.py
studlis/static/bootstrap5.3/css/__init__.py
studlis/static/bootstrap5.3/css/bootstrap-grid.css
studlis/static/bootstrap5.3/css/bootstrap-grid.min.css
studlis/static/bootstrap5.3/css/bootstrap-grid.rtl.css
studlis/static/bootstrap5.3/css/bootstrap-grid.rtl.min.css
studlis/static/bootstrap5.3/css/bootstrap-reboot.css
studlis/static/bootstrap5.3/css/bootstrap-reboot.min.css
studlis/static/bootstrap5.3/css/bootstrap-reboot.rtl.css
studlis/static/bootstrap5.3/css/bootstrap-reboot.rtl.min.css
studlis/static/bootstrap5.3/css/bootstrap-utilities.css
studlis/static/bootstrap5.3/css/bootstrap-utilities.min.css
studlis/static/bootstrap5.3/css/bootstrap-utilities.rtl.css
studlis/static/bootstrap5.3/css/bootstrap-utilities.rtl.min.css
studlis/static/bootstrap5.3/css/bootstrap.min.css
studlis/static/bootstrap5.3/css/bootstrap.rtl.css
studlis/static/bootstrap5.3/css/bootstrap.rtl.min.css
studlis/static/bootstrap5.3/js/__init__.py
studlis/static/bootstrap5.3/js/bootstrap.bundle.min.js
studlis/static/fontawesome/__init__.py
studlis/static/fontawesome/css/__init__.py
studlis/static/fontawesome/css/all.min.css
studlis/static/fontawesome/webfonts/__init__.py
studlis/static/fontawesome/webfonts/fa-brands-400.ttf
studlis/static/fontawesome/webfonts/fa-brands-400.woff2
studlis/static/fontawesome/webfonts/fa-regular-400.ttf
studlis/static/fontawesome/webfonts/fa-regular-400.woff2
studlis/static/fontawesome/webfonts/fa-solid-900.ttf
studlis-0.0.10.dist-info/METADATA
studlis-0.0.10.dist-info/WHEEL
studlis-0.0.10.dist-info/licenses/LICENCE.md
studlis-0.0.10.dist-info/RECORD
