Metadata-Version: 2.4
Name: studlis
Version: 0.0.10
Summary: Studlis is a scriptable project manager providing a frontend for reviews.
Project-URL: Homepage, https://github.com/umitnrodemund/studlis
Project-URL: Issues, https://github.com/umitnrodemund/studlis/issues
Author-email: Rodemund Niklas <nrodemund@gmail.com>
License: Copyright (c) 2018 The Python Packaging Authority
License-File: LICENCE.md
Classifier: Operating System :: OS Independent
Classifier: Programming Language :: Python :: 3
Requires-Python: >=3.8
Requires-Dist: aiofiles
Requires-Dist: aiohttp
Requires-Dist: aiosqlite
Requires-Dist: fastapi
Requires-Dist: mako
Requires-Dist: openpyxl
Requires-Dist: uvicorn
